credici/.DS_Store
credici/__init__.py
credici/async_/.DS_Store
credici/async_/__init__.py
credici/async_/async_client/async_client.py
credici/async_/async_storage/__init__.py
credici/async_/async_storage/async_postgres_storage.py
credici/async_/async_storage/async_storage.py
credici/async_/cycle.py
credici/async_/ledger.py
credici/async_/status.py
credici/exception.py
credici/schema/.DS_Store
credici/schema/__init__.py
credici/schema/postgres_db_schema.py
credici/schema/storage_schema.py
credici/sync_/.DS_Store
credici/sync_/__init__.py
credici/sync_/client/client.py
credici/sync_/credit_transaction.py
credici/sync_/cycle.py
credici/sync_/ledger.py
credici/sync_/storage/__init__.py
credici/sync_/storage/postgres_storage.py
credici/sync_/storage/storage.py
credici/user/__init__.py
credici/user/user.py
credici-0.1.10.dist-info/LICENSE.txt
credici-0.1.10.dist-info/METADATA
credici-0.1.10.dist-info/WHEEL
credici-0.1.10.dist-info/RECORD
