Metadata-Version: 2.1
Name: credici
Version: 0.1.10
Summary: Python library for Credici
Author: bosketto
Requires-Python: >=3.11,<4.0
Classifier: Programming Language :: Python :: 3
Classifier: Programming Language :: Python :: 3.11
Classifier: Programming Language :: Python :: 3.12
Requires-Dist: asyncpg (>=0.28.0,<0.29.0)
Requires-Dist: psycopg[binary] (>=3.1.17,<4.0.0)
Requires-Dist: pydantic (>=2.3.0,<3.0.0)
Requires-Dist: pydantic-settings (>=2.1.0,<3.0.0)
Requires-Dist: pytest (>=8.0.0,<9.0.0)
Requires-Dist: pytest-cov (>=4.1.0,<5.0.0)
Requires-Dist: sqlalchemy[asyncio] (>=2.0.21,<3.0.0)
